awstestutils/__init__.py
awstestutils/cleanup.py
awstestutils-1.0.0.dist-info/DESCRIPTION.rst
awstestutils-1.0.0.dist-info/METADATA
awstestutils-1.0.0.dist-info/RECORD
awstestutils-1.0.0.dist-info/WHEEL
awstestutils-1.0.0.dist-info/metadata.json
awstestutils-1.0.0.dist-info/top_level.txt
