Metadata-Version: 2.0
Name: awstestutils
Version: 1.0.0
Summary: Artifacts to test dependencies with AWS using boto3
Home-page: https://github.com/etoccalino/aws-test-utils
Author: Elvio Toccalino
Author-email: me@etoccalino.com
License: BSD
Download-URL: https://github.com/etoccalino/aws-test-utils/archive/v0.1.6.zip
Keywords: aws,boto3,testing,tool
Platform: UNKNOWN
Classifier: Development Status :: 5 - Production/Stable
Classifier: Intended Audience :: Developers
Classifier: License :: OSI Approved :: BSD License
Classifier: Programming Language :: Python :: 3
Classifier: Topic :: Software Development :: Testing
Classifier: Topic :: Utilities
Requires-Dist: boto3
